src/__init__.py
unidata/404.html
unidata/__init__.py
unidata/base.html
unidata/main.html
unidata/mkdocs_theme.yml
unidata/assets/images/favicon.ico
unidata/assets/images/icons/bitbucket-670608a71a.svg
unidata/assets/images/icons/github-1da075986e.svg
unidata/assets/images/icons/gitlab-5ad3f9f9e5.svg
unidata/assets/javascripts/application-eaeb7b21e3.js
unidata/assets/javascripts/modernizr-e826f8942a.js
unidata/assets/javascripts/lunr/lunr.da.js
unidata/assets/javascripts/lunr/lunr.de.js
unidata/assets/javascripts/lunr/lunr.du.js
unidata/assets/javascripts/lunr/lunr.es.js
unidata/assets/javascripts/lunr/lunr.fi.js
unidata/assets/javascripts/lunr/lunr.fr.js
unidata/assets/javascripts/lunr/lunr.hu.js
unidata/assets/javascripts/lunr/lunr.it.js
unidata/assets/javascripts/lunr/lunr.jp.js
unidata/assets/javascripts/lunr/lunr.multi.js
unidata/assets/javascripts/lunr/lunr.no.js
unidata/assets/javascripts/lunr/lunr.pt.js
unidata/assets/javascripts/lunr/lunr.ro.js
unidata/assets/javascripts/lunr/lunr.ru.js
unidata/assets/javascripts/lunr/lunr.stemmer.support.js
unidata/assets/javascripts/lunr/lunr.sv.js
unidata/assets/javascripts/lunr/lunr.tr.js
unidata/assets/javascripts/lunr/tinyseg.js
unidata/assets/stylesheets/application-37fa87ea8f.css
unidata/assets/stylesheets/application-624922a329.palette.css
unidata/partials/disqus.html
unidata/partials/footer.html
unidata/partials/header.html
unidata/partials/language.html
unidata/partials/nav-item.html
unidata/partials/nav.html
unidata/partials/search.html
unidata/partials/social.html
unidata/partials/source.html
unidata/partials/tabs-item.html
unidata/partials/tabs.html
unidata/partials/toc-item.html
unidata/partials/toc.html
mkdocs_unidata-2.0.3.dist-info/LICENSE
mkdocs_unidata-2.0.3.dist-info/METADATA
mkdocs_unidata-2.0.3.dist-info/WHEEL
mkdocs_unidata-2.0.3.dist-info/entry_points.txt
mkdocs_unidata-2.0.3.dist-info/top_level.txt
mkdocs_unidata-2.0.3.dist-info/RECORD
