Metadata-Version: 2.1
Name: mkdocs-unidata
Version: 2.0.3
Summary: Custom Material Design theme for MkDocs
Home-page: http://mjames-upc.github.io/mkdocs-unidata/
Author: Unidata
Author-email: support@unidata.ucar.edu
License: MIT
Keywords: mkdocs,documentation,theme
License-File: LICENSE
Requires-Dist: fontawesome-markdown (==0.2.6)
